{
	"1star"			: "简单力量礼物",
	"2star"			: "可爱力量礼物",
	"3star"			: "奇妙力量礼物",
	"bonus"			: "额外礼物",
	"quick"			: "快速礼物",
	"bounty"		: "奖励礼物",
	"blessing"		: "祝福礼物",
	"burden"		: "负担礼物",
	"upgrade"		: "升级礼物",
	"unknown"		: "未知礼物",
	
	"memory"		: "回忆",
	"effects"		: "礼物效果",
	"gift_records"	: "礼物记录",
	
	"records" : {
		"gets"		: "收到的次数",
		"uses"		: "携带该礼物开始的战斗",
		"loves"		: "使用该礼物的爱",
		"loses"		: "使用该礼物时的心碎",
		"synapse"	: "从连接突触中带走的次数",
		"gives"		: "给出的次数",
	},
	
	"quick_gift_menu" : {
		"use_confirm"	: "激活这个快速礼物？",
		"use_discard"	: "抛弃这个快速礼物？",
		"list_title"	: "[NAME]的快速礼物",
		"active_title"	: "激活快速礼物",
		"empty"			: "空",
		"none"			: "无",
	},
	
	"rad_tut_common"	: "被点亮的礼物会永久在所有游戏模式中揭示",
	"rad_tut_power"		: "被点亮的力量礼物会永久在所有游戏模式中揭示，\n且可以在快速挑战中使用",
	"rad_tut_quick"		: "被点亮的快速礼物会永久在所有游戏模式中揭示，\n且任何未使用的快速礼物都会在每一局之间被保留",
	"rad_tut_upgrade"	: "点亮这个礼物来解锁一个永久的升级！",
	"find_common"		: "这个礼物可以在任何正常遭遇中从任何怪物处收到",
	"find_tower"		: "这个礼物可以从高塔里的任何怪物处收到",
	"find_upgrade"		: "这个礼物仅能够从最终遭遇处收到",
	"upgrade_error"		: "这个礼物现在无法被找到，\n因为它能够为某样被锁定的东西升级",
	"unknown_effects"	: "点亮这个礼物以揭露其详细的效果列表",
	"forgotten_effects"	: "你对这个礼物的记忆被某种效果阻隔了",
	"reveal_story"		: "在故事模式中收到这张礼物卡\n以在这里显示它",
	"reveal_any_mode"	: "在任何模式中收到这张礼物卡\n以在这里显示它",
	"unlock_explain"	: "在特定的梦境未被满足之前\n这个礼物不会在这里显示",
	"unlock_monster"	: "在特定的怪物被爱之前这个礼物不会出现",
	"unlock_character"	: "在特定的角色解锁之前这个礼物不会出现",
	
	"special_card_desc" : "点亮这个礼物！",

	"gift_groups" : {
		"group_can_radiate"	: "可以被点亮",
		
		"group_all_power"	: "全部力量礼物",
		"found_all_power"	: "发现的力量礼物",
		"rad_all_power"		: "点亮的力量礼物",
		"group_passive"		: "被动增益礼物",
		"found_passive"		: "发现的被动增益礼物",
		"rad_passive"		: "点亮的被动增益礼物",
		"group_effect"		: "被动效果礼物",
		"found_effect"		: "发现的被动效果礼物",
		"rad_effect"		: "点亮的被动效果礼物",
		"group_successive"	: "连续效果礼物",
		"found_successive"	: "发现的连续效果礼物",
		"rad_successive"	: "点亮的连续效果礼物",
		"group_fortifying"	: "加固礼物",
		"found_fortifying"	: "发现的加固礼物",
		"rad_fortifying"	: "点亮的加固礼物",
		"group_panic"		: "恐慌攻击礼物",
		"found_panic"		: "发现的恐慌攻击礼物",
		"rad_panic"			: "点亮的恐慌攻击礼物",
		"group_charge"		: "蓄力攻击礼物",
		"found_charge"		: "发现的蓄力攻击礼物",
		"rad_charge"		: "点亮的蓄力攻击礼物",
		"group_heart"		: "心心子弹礼物",
		"found_heart"		: "发现的心心子弹礼物",
		"rad_heart"			: "点亮的心心子弹礼物",
		"group_heart_e"		: "心之元素礼物",
		"found_heart_e"		: "发现的心之元素礼物",
		"rad_heart_e"		: "点亮的心之元素礼物",
		"group_feather"		: "羽毛子弹礼物",
		"found_feather"		: "发现的羽毛子弹礼物",
		"rad_feather"		: "点亮的羽毛子弹礼物",
		"group_feather_e"	: "羽毛元素礼物",
		"found_feather_e"	: "发现的羽毛元素礼物",
		"rad_feather_e"		: "点亮的羽毛元素礼物",
		"group_star"		: "星星子弹礼物",
		"found_star"		: "发现的星星子弹礼物",
		"rad_star"			: "点亮的星星子弹礼物",
		"group_star_e"		: "星星元素礼物",
		"found_star_e"		: "发现的星星元素礼物",
		"rad_star_e"		: "点亮的星星元素礼物",
		"group_helper"		: "帮手礼物",
		"found_helper"		: "发现的帮手礼物",
		"rad_helper"		: "点亮的帮手礼物",
		
		"group_all_bonus"	: "所有额外礼物",
		"found_all_bonus"	: "发现的额外礼物",
		"rad_all_bonus"		: "点亮的额外礼物",
		"group_status"		: "状态额外礼物",
		"found_status"		: "发现的状态额外礼物",
		"rad_status"		: "点亮的状态额外礼物",
		"group_stock"		: "后备额外礼物",
		"found_stock"		: "发现的后备额外礼物 ",
		"rad_stock"			: "点亮的后备额外礼物 ",
		"group_tetrids"		: "棱晶额外礼物",
		"found_tetrids"		: "发现的棱晶额外礼物 ",
		"rad_tetrids"		: "点亮的棱晶额外礼物 ",
		
		"group_all_quick"	: "所有快速礼物",
		"found_all_quick"	: "快速礼物发现的",
		"rad_all_quick"		: "快速礼物点亮的",
		"group_q_boost"		: "快速增益礼物",
		"found_q_boost"		: "发现的快速增益礼物 ",
		"rad_q_boost"		: "点亮的快速增益礼物 ",
		"group_q_effect"	: "快速效果礼物",
		"found_q_effect"	: "发现的快速效果礼物 ",
		"rad_q_effect"		: "点亮的快速效果礼物 ",
		"group_q_infusion"	: "快速输注礼物",
		"found_q_infusion"	: "发现的快速输注礼物 ",
		"rad_q_infusion"	: "点亮的快速输注礼物 ",
		"group_q_helper"	: "快速帮手礼物",
		"found_q_helper"	: "发现的快速帮手礼物 ",
		"rad_q_helper"		: "点亮的快速帮手礼物 ",
		"group_q_redraw"	: "快速重抽礼物",
		"found_q_redraw"	: "发现的快速重抽礼物 ",
		"rad_q_redraw"		: "点亮的快速重抽礼物 ",
		
		"group_all_bounty"	: "全部奖励礼物",
		"found_all_bounty"	: "发现的奖励礼物",
		"rad_all_bounty"	: "点亮的奖励礼物",
		"group_bnt_normal"	: "祝福奖励礼物",
		"found_bnt_normal"	: "发现的祝福奖励礼物 ",
		"rad_bnt_normal"	: "点亮的祝福奖励礼物 ",
		"group_bnt_tough"	: "负担奖励礼物",
		"found_bnt_tough"	: "发现的负担奖励礼物 ",
		"rad_bnt_tough"		: "点亮的负担奖励礼物 ",
		
		"group_all_blessing"	: "全部祝福",
		"found_all_blessing"	: "发现的祝福 ",
		"rad_all_blessing"		: "点亮的祝福 ",
		"group_bls_unique"		: "独特祝福",
		"found_bls_unique"		: "发现的独特祝福 ",
		"rad_bls_unique"		: "点亮的独特祝福 ",
		"group_bls_shamble"		: "晃晃祝福",
		"found_bls_shamble"		: "发现的晃晃祝福 ",
		"rad_bls_shamble"		: "点亮的晃晃祝福 ",
		"group_bls_guardian"	: "守护者祝福",
		"found_bls_guardian"	: "发现的守护者祝福 ",
		"rad_bls_guardian"		: "点亮的守护者祝福 ",
		"group_bls_glyph"		: "眼睛符文祝福",
		"found_bls_glyph"		: "发现的眼睛符文祝福 ",
		"rad_bls_glyph"			: "点亮的眼睛符文祝福 ",
		"group_bls_zaramech"	: "扎拉机械祝福",
		"found_bls_zaramech"	: "发现的扎拉机械祝福 ",
		"rad_bls_zaramech"		: "点亮的扎拉机械祝福 ",
		"group_bls_flora"		: "玻璃植物祝福",
		"found_bls_flora"		: "发现的玻璃植物祝福 ",
		"rad_bls_flora"			: "点亮的玻璃植物祝福 ",
		"group_bls_veyeral"		: "维目尔祝福",
		"found_bls_veyeral"		: "发现的维目尔祝福 ",
		"rad_bls_veyeral"		: "点亮的维目尔祝福 ",
		"group_bls_special"		: "特别祝福",
		"found_bls_special"		: "发现的特别祝福 ",
		"rad_bls_special"		: "点亮的特别祝福 ",
		
		"group_all_burden"		: "全部负担",
		"found_all_burden"		: "发现的负担 ",
		"rad_all_burden"		: "点亮的负担 ",
		"group_bdn_unique"		: "独特负担",
		"found_bdn_unique"		: "发现的独特负担 ",
		"rad_bdn_unique"		: "点亮的独特负担 ",
		"group_bdn_shamble"		: "晃晃负担",
		"found_bdn_shamble"		: "发现的晃晃负担 ",
		"rad_bdn_shamble"		: "点亮的晃晃负担 ",
		"group_bdn_guardian"	: "守护者负担",
		"found_bdn_guardian"	: "发现的守护者负担 ",
		"rad_bdn_guardian"		: "点亮的守护者负担 ",
		"group_bdn_glyph"		: "眼睛符文负担",
		"found_bdn_glyph"		: "发现的眼睛符文负担 ",
		"rad_bdn_glyph"			: "点亮的眼睛符文负担 ",
		"group_bdn_zaramech"	: "扎拉机械负担",
		"found_bdn_zaramech"	: "发现的扎拉机械负担 ",
		"rad_bdn_zaramech"		: "点亮的扎拉机械负担 ",
		"group_bdn_flora"		: "玻璃植物负担",
		"found_bdn_flora"		: "发现的玻璃植物负担 ",
		"rad_bdn_flora"			: "点亮的玻璃植物负担 ",
		"group_bdn_veyeral"		: "维目尔负担",
		"found_bdn_veyeral"		: "发现的维目尔负担 ",
		"rad_bdn_veyeral"		: "点亮的维目尔负担 ",
		"group_bdn_special"		: "特别负担",
		"found_bdn_special"		: "发现的特别负担 ",
		"rad_bdn_special"		: "点亮的特别负担 ",
		
		"group_all_upgrade"	: "全部升级礼物",
		"found_all_upgrade"	: "发现的升级礼物 ",
		"rad_all_upgrade"	: "点亮的升级礼物 ",
		"group_her_heart"	: "她的心",
		"found_her_heart"	: "发现的她的心升级 ",
		"rad_her_heart"		: "点亮的她的心升级 ",
		"group_defect"		: "缺陷",
		"found_defect"		: "发现的缺陷升级 ",
		"rad_defect"		: "点亮的缺陷升级 ",
		"group_twin_heart"	: "双子之心",
		"found_twin_heart"	: "发现的双子之心升级 ",
		"rad_twin_heart"	: "点亮的双子之心升级 ",
		"group_the_devil"	: "恶魔",
		"found_the_devil"	: "发现的恶魔升级 ",
		"rad_the_devil"		: "点亮的恶魔升级 ",
		"group_event"		: "事件",
		"found_event"		: "发现的事件升级 ",
		"rad_event"			: "点亮的事件升级 ",
		"group_solara"		: "索拉娜的礼物店",
		"found_solara"		: "发现的索拉娜的礼物店升级 ",
		"rad_solara"		: "点亮的索拉娜的礼物店升级 ",
	},
	
	
	
	"tag_effects" : {
		"tag_no_heal" 			: "|C4|这个礼物会延长你的生命条，但它不会治疗你。",
		"tag_low_hp_cap"		: "|C4|这个效果不会将你的生命值降低到1点以下。",
		"tag_successive" 		: "仅当该礼物从战斗中收到时，该效果会立刻生效。",
		"tag_low_health"		: "低生命值阈值通常为7.5生命值|L|25%的最大生命值若其更高|L|90%的最大生命值若其更低",
		"tag_per_battle"		: "这个效果每场战斗可以触发一次。",
		"tag_multi_trigger" 	: "这个效果每场战斗可以触发[VAL1]次。",
		"tag_no_effect" 		: "|C4|这个礼物在战斗中没有效果。",
		"tag_wear_off" 			: "|C4|这个效果会在每场战斗结束后消失。",
		"tag_bonus"				: "额外礼物可以被多次收到。",
		"tag_extra_mites"		: "仅当你拥有跳虫帮手时这个礼物才会出现。",
		"tag_extra_magnets"		: "仅当你拥有磁力石时这个礼物才会出现。",
		"tag_quick_s"			: "|C4|这个效果会在一场战斗后消失。",
		"tag_quick"				: "|C4|这个效果会在[VAL1]场战斗后消失。",
		"tag_quick_perm"		: "|C3|任何从这个礼物获得的永久升级在礼物消失后也不会消失！",
		"tag_aura_dps" 			: "对范围内的目标造成[VAL1]每秒伤害|L|对全场目标造成[VAL2]每秒伤害",
		"tag_overflow"			: "能量可以溢出直至最大能量的一倍。",
		"tag_radiated_add" 		: "|C4|对你施加[VAL1]点|C3|光耀生命。|C4|",
		"tag_radiated_1" 		: "|C3|光耀生命|C4|每十秒会削减1点生命值，在仅剩1点生命时停止。|L||C0|该速率受到[RADIANT]防御影响。",
		"tag_radiated_2" 		: "|C3|光耀生命|C0|仅能够在战斗结束时被清除。",
		"tag_bleeding_add" 		: "|C4|对你施加[VAL1]点|C3|流血生命。|C4|",
		"tag_bleeding_1" 		: "|C3|流血生命|C4|每十秒会削减1点生命值，在仅剩1点生命时停止。|L||C0|该速率受到[VOID]防御影响。",
		"tag_bleeding_2" 		: "|C3|流血生命|C0|仅能够在战斗结束时被清除。",
		"tag_burning_add" 		: "|C4|对你施加[VAL1]点|C3|燃烧生命。|C4|",
		"tag_burning_1" 		: "|C3|燃烧生命|C4|每十秒会烧掉2.5点生命值，在仅剩1点生命时停止。|L|静止不动会使得该速率变为3倍！|L||C0|该速率受到[BURN]防御影响。",
		"tag_burning_2" 		: "|C3|燃烧生命|C0|失去的生命量可以通过全速移动来削减。",
		"tag_burning_3" 		: "[DRAINING_CLEAR]",
		"tag_overload_add" 		: "|C4|对你施加[VAL1]点|C3|过载生命。|C4|",
		"tag_overload_1" 		: "|C3|过载生命|C4|每十秒会电离2.5点生命值，在仅剩1点生命时停止。|L||C0|该速率受到[ZAP]防御影响。",
		"tag_overload_2" 		: "|C3|过载生命|C0|可以被用于快速恢复消耗掉的蓄力能量。这同样能够减少失去的生命。",
		"tag_overload_3" 		: "[DRAINING_CLEAR]",
		"tag_poisoned_add" 		: "|C4|对你施加[VAL1]点|C3|毒素生命。|C4|",
		"tag_poisoned_1" 		: "|C3|毒素生命|C4|每十秒会削减2.5点生命值，在仅剩1点生命时停止。|L||C0|该速率受到[TOXIC]防御影响。",
		"tag_poisoned_2" 		: "|C3|毒素生命|C0|失去的生命量可以通过静止不动来削减。",
		"tag_poisoned_3" 		: "[DRAINING_CLEAR]",
		"tag_draining_clear" 	: "所有生命流失效果在战斗结束时都会被清除。",
		"tag_draining" 			: "|C4|每种生命流失效果的速率取决于其元素种类与你的对应防御。|C0|你可以在属性界面找到现有效果的更多细节。",
	},
	"status_effects" : {
		"heal+_hp" 				: "回复[VAL1]点生命",
		"heal%_hp" 				: "回复[VAL1]%的最大生命",
		"heal+_en" 				: "立刻回复[VAL1]点能量",
		"heal%_en" 				: "立刻回复[VAL1]%的最大能量",
		"heal%_overflow_en" 	: "立刻回复且溢出[VAL1]%的最大能量",
		"+_karma" 				: "获得[VAL1]因果",
		"+_panics_s" 			: "获得1个恐慌攻击",
		"+_panics" 				: "获得[VAL1]个恐慌攻击",
		"+MP_manic_panics_s" 	: "获得1个|C3|狂热恐慌|C0|",
		"+MP_manic_panics" 		: "获得[VAL1]个|C3|狂热恐慌|C0|",
		"=MP_manic_panics" 		: "将所有的恐慌攻击转变为|C3|狂热恐慌|C0|",
		"0_manic_panics_1" 		: "|C3|狂热恐慌|C0|先于正常恐慌攻击被使用，且其大小会不断跳动。",
		"0_manic_panics_2" 		: "|C4|如果你在战斗中未使用狂热恐慌，在战斗结束时其中一个会被自动使用。|C0|（这不会使挑战失败）",
		"+_panic_polyps_s" 		: "获得1个|C3|恐慌之瘤|C0|",
		"+_panic_polyps" 		: "获得[VAL1]个|C3|恐慌之瘤|C0|",
		"0_panic_polyps" 		: "战斗中每20秒，一个|C3|恐慌之瘤|C0|会被转变为恐慌攻击，只要你目前的恐慌攻击数量少于[VAL_CAP]。",
		"0_quick_polyps" 		: "|C3|任何剩余的恐慌之瘤都会延续到后续的战斗中！",
		"+_soft_max_hp" 		: "最大生命+[VAL1] |C3|（永久）",
		"+_soft_max_en" 		: "最大能量+[VAL1] |C3|（永久）",
		"+_soft_damage_bonus" 	: "为总伤害调整倍率加上[VAL1]%|C3|（永久）",
		"+_soft_crit_rate" 		: "所有基础子弹变为|C3|暴击子弹|C0|的比率增加[VAL1]%|C3|（永久）",
		"+_soft_radiant_res" 	: "[RADIANT]防御+[VAL1] |C3|（永久）",
		"+_soft_void_res" 		: "[VOID]防御+[VAL1] |C3|（永久）",
		"+_soft_burn_res" 		: "[BURN]防御+[VAL1] |C3|（永久）",
		"+_soft_zap_res" 		: "[ZAP]防御+[VAL1] |C3|（永久）",
		"+_soft_toxic_res" 		: "[TOXIC]防御+[VAL1] |C3|（永久）",
		"+_glass_hearts_s" 		: "获得1个|C3|玻璃之心|C0|",
		"+_glass_hearts" 		: "获得[VAL1]个|C3|玻璃之心|C0|",
		"0_glass_hearts_1" 		: "每个|C3|玻璃之心|C0|能够将一次受击的伤害减半。",
		"+_chrome_hearts_1s" 	: "获得1个|C3|铬之心|C0|",
		"+_chrome_hearts_1" 	: "获得[VAL1]个|C3|铬之心|C0|",
		"+_chrome_hearts_2" 	: "每个|C3|铬之心|C0|能够防止你的连击被打断一次。",
		"+_chrome_hearts_3" 	: "|C3|铬之心|C0|在你受到伤害时能够保护你的提取奖励。",
		"+_once_revive_s" 		: "获得1个|C3|后备复活|C0|",
		"+_once_revive" 		: "获得[VAL1]个|C3|后备复活|C0|",
		"0_once_revive_1" 		: "|C3|后备复活|C0|在你受到能够导致心碎的伤害时能够立刻将你回复到1点生命。|L||C4|它们在使用后不会再生。",
		"+_once_denial_s" 		: "获得1个|C3|后备否认之盾|C0|",
		"+_once_denial" 		: "获得[VAL1]个|C3|后备否认之盾s|C0|",
		"0_once_denial" 		: "每个|C3|后备否认之盾|C0|在战斗中能够阻挡一次受击。|L||C4|它们在使用后不会再生。",
		"+_reserve_hp" 			: "获得[VAL1]点|C3|后备生命|C0|",
		"0_reserve_hp_1" 		: "|C3|后备生命|C0|在战斗中会以每5秒1点生命的速率回复你失去的生命，直至全部使用完毕。",
		"0_reserve_hp_2" 		: "|C3|后备生命|C0|在你生命值全满时不会被使用。",
		"+_blue_count_s" 		: "生成一个围绕型蓝色维目尔帮手！",
		"+_blue_count" 			: "生成[VAL1]个围绕型蓝色维目尔帮手！",
		"+_misfits_count" 		: "生成[VAL1]个围绕型不具之心帮手！",
		"+_extra_mites_s" 		: "你能够吸引1只额外跳虫帮手。",
		"+_extra_mites" 		: "你能够吸引[VAL1]只额外跳虫帮手。",
		"+_extra_magnets_s" 	: "你能够吸引1个额外磁力石。",
		"+_extra_magnets" 		: "你能够吸引[VAL1]个额外磁力石。",
		
		"hurt-_hp_1" 			: "|C4|失去[VAL1]点生命",
		"hurt-_hp_2" 			: "[LOW_HP_CAP]",
		"hurt%_hp_1" 			: "|C4|失去[VAL1]%的当前生命",
		"hurt%_hp_2" 			: "[LOW_HP_CAP]",
		"hurt%_reserve_hp_1" 	: "|C4|失去[VAL1]%的当前生命然后获得等同于失去生命量的|C3|后备生命。|C4|",
		"hurt%_reserve_hp_2" 	: "[LOW_HP_CAP]",
		"+_bleed_hearts_s" 		: "|C4|获得1个|C3|流血之心|C4|",
		"+_bleed_hearts" 		: "|C4|获得[VAL1]个|C3|流血之心|C4|",
		"0_bleed_hearts_1" 		: "|C3|流血之心|C4|在你受击时会施加4点|C3|流血生命|C4|，即使伤害被阻挡。",
		"0_bleed_hearts_2" 		: "全连击能够移除一个|C3|流血之心。|C0|",
		"+_stress_hearts_s" 	: "|C4|获得1个|C3|压力之心|C4|",
		"+_stress_hearts" 		: "|C4|获得[VAL1]个|C3|压力之心|C4|",
		"0_stress_hearts_1" 	: "|C3|压力之心|C4|在你受到伤害后会将你1点生命值以外的当前生命转变为|C3|后备生命。|C4| ",
		"0_stress_hearts_2" 	: "|C3|后备生命|C0|每5秒能够回复1点生命",
		"0_stress_hearts_3" 	: "全连击能够移除一个|C3|压力之心。|C0|",
		"+_trauma_hearts_s" 	: "|C4|获得1个|C3|创伤之心|C4|",
		"+_trauma_hearts" 		: "|C4|获得[VAL1]个|C3|创伤之心s|C4|",
		"0_trauma_hearts_1" 	: "|C3|创伤之心|C4|在你受到伤害时会永久降低你的1点最大生命。",
		"0_trauma_hearts_2" 	: "每场战斗后会移除1个未生效的|C3|创伤之心。|C0|",
	},
	"main_effects" : {
		"+_max_hp" 				: "最大生命+[VAL1]",
		"-_max_hp" 				: "|C4|最大生命-[VAL1]",
		"+_radiant_res" 		: "[RADIANT]防御+[VAL1]",
		"+_void_res" 			: "[VOID]防御+[VAL1]",
		"+_burn_res" 			: "[BURN]防御+[VAL1]",
		"+_zap_res" 			: "[ZAP]防御+[VAL1]",
		"+_toxic_res" 			: "[TOXIC]防御+[VAL1]",
		"-_radiant_res" 		: "[RADIANT]|C4|防御-[VAL1]",
		"-_void_res" 			: "[VOID]|C4|防御-[VAL1]",
		"-_burn_res" 			: "[BURN]|C4|防御-[VAL1]",
		"-_zap_res" 			: "[ZAP]|C4|防御-[VAL1]",
		"-_toxic_res" 			: "[TOXIC]|C4|防御-[VAL1]",
		"0_radiant_pow" 		: "每点[RADIANT]防御能够为总伤害调整倍率加上[VAL1]%，最多15单元。",
		"0_void_pow" 			: "每点[VOID]防御能够为总伤害调整倍率加上[VAL1]%，最多15单元。",
		"0_burn_pow" 			: "每点[BURN]防御能够为总伤害调整倍率加上[VAL1]%，最多15单元。",
		"0_zap_pow" 			: "每点[ZAP]防御能够为总伤害调整倍率加上[VAL1]%，最多15单元。",
		"0_toxic_pow" 			: "每点[TOXIC]防御能够为总伤害调整倍率加上[VAL1]%，最多15单元。",
		"0_low_pow" 			: "低于2的防御数值仍能够提供至少2单元的该效果。",
		"0_all_pow_1" 			: "每点防御能够为总伤害调整倍率加上[VAL1]%，每种元素最多15单元。",
		"0_all_pow_2" 			: "每种元素低于2的防御数值仍能够提供至少2单元的该效果。这意味着至少能够保证10单元的该效果。",
		"+_damage_bonus" 		: "为总伤害调整倍率加上[VAL1]%|C3|",
		"-_damage_bonus" 		: "|C4|为总伤害调整倍率减去[VAL1]%|C3|",
		"+_move_speed" 			: "移动速度+[VAL1]",
		"-%_move_speed" 		: "|C4|收到该礼物时，你当前的移动速度将减少[VAL1]%。",
		"+_combo_time_s" 		: "延长爱之连击时间1秒。",
		"+_combo_time" 			: "延长爱之连击时间[VAL1]秒。",
		"+_immune_time" 		: "延长受到伤害后的无敌时间[VAL1]秒。",
		"-%r_immune_time_1" 	: "|C4|收到该礼物时，当前受到伤害后的无敌时间将减少[VAL1]%。",
		"-%r_immune_time_2" 	: "无敌时间无法被降至0.5秒以下。",
		"+_shot_speed_mod" 		: "所有类型基础子弹的移动速度增加[VAL1]%。",
		"-_shot_speed_mod" 		: "|C4|所有类型基础子弹的移动速度减少[VAL1]%。",
		"+_shot_spread_1" 		: "|C4|所有类型基础子弹的随机散射弧度增加[VAL1]度。",
		"+_shot_spread_2" 		: "|C4|蓄力射击子弹与帮手子弹同样会被轻微影响。",
		"+_crit_rate" 			: "所有基础子弹变为|C3|暴击子弹|C0|的比率增加[VAL1]%",
		"-_crit_rate" 			: "|C4|所有基础子弹变为|C3|暴击子弹|C4|的比率降低[VAL1]%",
		"+_crit_bonus" 			: "|C3|所有暴击子弹|C0|的额外伤害增加[VAL1]%",
		"-_crit_bonus" 			: "|C4||C3|所有暴击子弹|C4|的额外伤害降低[VAL1]%",
		"+_crit_radius" 		: "|C3|暴击泡泡|C0|的半径增加[VAL1]像素",
		"+_crit_time" 			: "|C3|暴击泡泡|C0|的持续时间增加[VAL1]秒",
		"+_shot_size_bonus"		: "所有基础子弹大小增加[VAL1]%",
		"=_element_overload_1" 	: "将所有基础子弹，蓄力攻击与恐慌攻击的伤害转变为[ELEMENT[VAL1]]。",
		"=_element_overload_2" 	: "每种已经是[ELEMENT[VAL1]]的子弹会获得+10%伤害。|L|（乘算，但无法叠加）",
	},
	"effect_effects" : {
		"+_health_gain" 		: "每场战斗后回复[VAL1]生命。",
		"+_reserve_gain_1" 		: "每场战斗后获得|C3|[VAL1]后备生命。|C0|",
		"+_reserve_gain_2" 		: "本效果获得的|C3|后备生命|C0|无法超过你的最大生命。",
		"+_karma_bonus" 		: "每场战斗后获得[VAL1]额外因果。",
		"+_inspire_hp_1" 		: "每场战斗后|C3|永久|C0|增加[VAL1]点激励最大生命，且在生命条延长时回复[VAL1]生命。",
		"+_inspire_hp_2" 		: "|C4|最多能够从任何带有这种激励效果的礼物中获得[VAL_CAP]点最大生命。",
		"+_inspire_dmg_1" 		: "每场战斗后总伤害调整倍率|C3|永久|C0|激励+[VAL1]%。",
		"+_inspire_dmg_2" 		: "|C4|最多能够从任何带有这种激励效果的礼物中获得+[VAL_CAP]%伤害。",
		"+_regen_low" 			: "如果你的生命值低于8点，则能够在战斗中以每秒[VAL1]点生命的速率回复",
		"+_regen_all" 			: "你的生命值能够在战斗中以每秒[VAL1]点生命的速率回复",
		"+_combo_heal_1" 		: "每次大于10%的连击结束时你能够轻微回复。",
		"+_combo_heal_2" 		: "回复量会随连击比例增长，在全连击时回复[VAL1]点生命。",
		"=_fear_sense_1" 		: "怪物当前的恐惧值会显示在怪物的恐惧条旁边。",
		"=_fear_sense_2" 		: "怪物的所有可破坏部件都会独立显示小型恐惧条。",
		"=_fear_sense_3" 		: "你的所有攻击都会显示准确的伤害数字。",
		"+_glass_petal_1" 		: "你所拥有的每点生命值会为总伤害调整倍率加上[VAL1]%",
		"+_glass_petal_2" 		: "当你的生命值全满时，该效果将乘以1.5倍。",
		"+_glass_petal_3" 		: "当你的生命值全满时，所有基础子弹大小增加[VAL_SIZE]%。",
		"=_screen_warp_1" 		: "离开屏幕会将你传送到另一边。",
		"=_screen_warp_2" 		: "屏幕传送会附带有0.6秒的无敌时间。|L||C4|这个效果有3秒的冷却时间。",
		"+_bullet_warp_1" 		: "当你的任何子弹离开屏幕时，它们会被传送到另外一边。",
		"+_bullet_warp_2s" 		: "每个子弹仅能水平传送一次，但垂直传送没有次数限制。",
		"+_bullet_warp_2" 		: "每个子弹仅能水平传送[VAL1]次，但垂直传送没有次数限制。",
		"+_chrome_regen_s" 		: "如果你没有剩余的|C3|铬之心，|C0|在战斗内每40秒能够生成一个。",
		"+_chrome_regen" 		: "当你的|C3|铬之心|C0|数量少于[VAL1]时，在战斗内每40秒能够生成一个。",
		"+_extra_monsters_s"	: "当这个礼物生效时能够揭露1个额外怪物选项。",
		"+_extra_monsters"		: "当这个礼物生效时能够揭露[VAL1]个额外怪物选项。",
		"=_power_roll" 			: "每个怪物都会提供2个|C3|力量礼物|C0||L|（或者2个该阶段能够提供的主要礼物）",
		"=_easy_challenge" 		: "所有挑战被替换为可轻易完成的挑战。",
		"+_key_power_1" 		: "战斗结束时，每个通过的挑战能够|C3|永久|C0|为总伤害调整倍率加上[VAL1]%。",
		"+_key_power_2" 		: "|C4|这种礼物效果最多可以提供+[VAL_CAP]%伤害。",
		"+_second_form_1" 		: "这些效果仅在你的生命值为0时激活。",
		"+_second_form_2" 		: "立刻回复50%的最大生命值。",
		"+_second_form_3" 		: "总伤害|C3|永久|C0|+[VAL_DMG]%。",
		"+_second_form_4" 		: "发散|C3|永久|C0|的[RADIANT]光环:|L|[AURA_DPS]",
		"+_shame_1" 			: "在战斗中受到伤害时，最大生命|C3|永久|C0|增加2点。",
		"+_shame_2s" 			: "[ONCE_PER_BATTLE]",
		"+_shame_2" 			: "[MULTI_PER_BATTLE]",
		"+_shame_3" 			: "|C4|这个效果会延长你的生命条，但它不会治疗你。",
		"+_shame_4" 			: "|C4|可以从带有羞愧效果的礼物中获得最多[VAL_CAP]点最大生命。",
		"+_frustration_1" 		: "每次受到伤害时，|C3|永久|C0|增加总伤害。",
		"+_frustration_2" 		: "每受到1点生命值的伤害，为总伤害调整倍率加上[VAL1]%。",
		"+_frustration_3" 		: "|C4|可以从带有激怒效果的礼物中获得最多+[VAL_CAP]%伤害。",
		"+_anxiety_1" 			: "当你的生命值低至闪烁警告时，|C3|焦虑|C0|效果会被激活。",
		"+_anxiety_2" 			: "当|C3|焦虑|C0|效果激活时，为总伤害调整倍率加上[VAL_DMG]%且所有基础子弹变大[VAL_SIZE]%。",
		"+_insecurity_1" 		: "受到伤害能够激活|C3|不安|C0|效果。",
		"+_insecurity_2" 		: "当|C3|不安|C0|效果激活时，为总伤害调整倍率加上[VAL_DMG]%且所有基础子弹变大[VAL_SIZE]%。",
		"+_loneliness_1" 		: "你在战斗中第一次受击后发散一个[VOID]光环。",
		"+_loneliness_2" 		: "[VOID]光环:|L|[AURA_DPS]",
		"=_chrome_heart" 		: "|C3|该礼物激活时，所有使用的铬之心会在战斗结束时恢复！",
		"+_rage_1" 				: "整场战斗中发散一个[BURN]光环。",
		"+_rage_2" 				: "[BURN]光环:|L|[AURA_DPS]",
		"+_spark_focus_1" 		: "在专注模式保持1.1秒后发散一个[ZAP]光环。",
		"+_spark_focus_2" 		: "[ZAP]光环:|L|[AURA_DPS]",
		"+_overgrowth_1" 		: "在战斗中经过50秒后，或者怪物的恐惧值降低到25%以下时，发散一个[TOXIC]光环",
		"+_overgrowth_2" 		: "[TOXIC]光环:|L|[AURA_DPS]",
		"+_fragile" 			: "如果你没有任何剩余的|C3|玻璃之心|C0|，且生命值未满，在每场战斗开始时你会获得一个。",
		"+_metal" 				: "仅当你没有剩余的后备否认之盾时，每次全连击获得一个|C3|后备否认之盾。|C0|",
		"+_chaos_bonus_1s" 		: "每场战斗后会发生以下效果中的一个:",
		"+_chaos_bonus_1" 		: "每场战斗后会发生以下效果中的[VAL1]个:",
		"+_chaos_bonus_2" 		: "激励总伤害+5%|C4|(最大+[VAL_CAP1]%)|C0||L|激励最大生命+2|C4|(最大+[VAL_CAP2])|C0||L|获得1个恐慌攻击|L|回复25%的最大生命|L|获得一个|C3|后备否认之盾|C0||C4|(直至拥有1个)|C0||L|获得一个|C3|玻璃之心|C0| |C4|(直至拥有4个)",
		"+_chaos_bonus_3" 		: "若选定的效果到达上限，则获得3因果。",
		"+_revita_heart_1" 		: "在战斗中每失去1点生命，为总伤害调整倍率加上[VAL_DMG]%。|L|（最大[CAP_DMG]%）",
		"+_revita_heart_2" 		: "在战斗中每失去1点生命，所有基础子弹大小增加[VAL_SIZE]%。|L|（最大[CAP_DMG]%）",
		"+_revita_heart_3" 		: "|C4|以上效果在每场战斗结束时会消失。",
		"+_revita_heart_4" 		: "每次你受到大于1点生命的伤害时生成1点|C3|后备生命。|C0|",
		"+_revive_1s" 			: "获得1个|C3|复活|C0|",
		"+_revive_1" 			: "获得[VAL1]个|C3|复活|C0|",
		"+_revive_2" 			: "每个|C3|复活|C0|在你受到会使你心碎的伤害时会将你回复到1点生命。",
		"0_revive" 				: "所有的|C3|复活|C0|在每场战斗后会重置。",
		"+_denial_1s" 			: "获得1个|C3|否认之盾|C0|",
		"+_denial_1" 			: "获得[VAL1]个|C3|否认之盾|C0|",
		"+_denial_2" 			: "每个|C3|否认之盾|C0|在战斗中能够阻挡一次受击。",
		"0_denial" 				: "所有的|C3|否认之盾|C0|在每场战斗后会重置。",
		
		"=_no_heart_bar" 		: "|C4|这个礼物生效时，你的生命条与心之护盾不可见。",
		"=_no_boss_bar" 		: "|C4|这个礼物生效时，怪物的恐惧条不可见。",
		"=_cant_focus" 			: "|C4|这个礼物生效时，你无法使用专注。",
		"=_focus_stop_1" 		: "|C4|你在专注时无法移动。",
		"=_focus_stop_2" 		: "在专注模式时，子弹散射减少80%。",
		"=_heavy_heart" 		: "|C4|在静止不动后一段时间，移动会变得迟缓。",
		"=_forgetful" 			: "|C4|所有礼物在收到前均显示为未知，即使已被点亮。",
		"=_amnesia" 			: "|C4|所有怪物显示为未知，即使已被点亮。",
		"=_half_hp_1" 			: "|C4|这个礼物生效时，你的最大生命减半。",
		"=_half_hp_2" 			: "|C4|所有改变最大生命的效果均减半，但在这个效果结束后会恢复正常数值。",
		"=_no_basic_1" 			: "|C4|你无法发射任何类型的基础子弹。",
		"=_no_basic_2" 			: "蓄力射击仍会被对应子弹类型的礼物所影响。",
		"=_invisible_shots" 	: "|C4|你的心或任何帮手发射的子弹将会隐形。",
		"=_cycle_shots_1" 		: "激活|C3|犹疑不决|C0|效果，令你的射击类型按以下顺序改变：|L|心心子弹|L|羽毛子弹|L|星星子弹",
		"=_cycle_shots_2" 		: "你的蓄力攻击也会改变为对应的类型。",
		"=_slow_shots" 			: "|C4|这个礼物生效时，你所有的子弹会以一半速度移动。",
		"=_gravity_shots" 		: "|C4|你所有的子弹会向场地下方落去。",
		"=_hard_challenge" 		: "|C4|挑战会倾向于变为更高难度等级，并可以达到新的最高难度。",
		"=_more_challenge" 		: "|C4|所有提供的礼物有更大几率被锁在挑战后。",
		"+_hp_drain_1" 			: "|C4|生命自动以每10秒[VAL1]点的速率流失。",
		"+_hp_drain_2" 			: "[LOW_HP_CAP]",
		"+_hp_loss_1" 			: "|C4|在每场战斗开始时失去[VAL1]点生命。",
		"+_hp_loss_2" 			: "[LOW_HP_CAP]",
		"+_combo_bleed" 		: "|C4|大于10%的连击被打断时会对你施加[VAL1]点|C3|流血生命。|C4|",
		"+_burn_scars" 			: "|C4|在每场战斗结束时对你施加[VAL1]点|C3|燃烧生命，|C4||C0|但最多不会使你的生命值降低到7点以下。",
		"+_hypercharge" 		: "|C4|每当怪物的恐惧减少20%时，对你施加[VAL1]点|C3|过载生命|C4|",
		"+_chaos_burden_1s" 	: "|C4|每场战斗后会发生以下效果中的一个:",
		"+_chaos_burden_1" 		: "|C4|每场战斗后会发生以下效果中的[VAL1]个:",
		"+_chaos_burden_2" 		: "|C4|获得1个流血之心（直至拥有3个）|L|获得1个压力之心（直至拥有1个）|L|获得2个创伤之心（直至拥有4个）|L|施加任意元素类型的4点生命流失",
		"+_chaos_burden_3" 		: "|C3|流血之心|C4|在你受击时会对你施加4点|C3|流血生命，|C4|即使伤害被阻挡。",
		"+_chaos_burden_4" 		: "|C3|压力之心|C4|在你受到伤害后会将你1点生命值以外的当前生命转变为|C3|后备生命。|C4|",
		"+_chaos_burden_5" 		: "全连击能够移除每种一个负担之心。",
	},
	"panic_effects" : {
		"+_damage_raw" 			: "恐慌攻击伤害+[VAL1]",
		"+_duration_s" 			: "恐慌攻击持续时间+1秒",
		"+_duration" 			: "恐慌攻击持续时间+[VAL1]秒",
		"-%_duration" 			: "|C4|收到该礼物时，当前恐慌攻击的持续时间减少[VAL1]%",
		"+_radius" 				: "恐慌攻击半径+[VAL1]像素",
		"-%_radius" 			: "|C4|收到该礼物时，当前的恐慌攻击半径减少[VAL1]%",
		"=_damage_type" 		: "恐慌攻击伤害被转变为[ELEMENT[VAL1]]伤害",
		"+_entropy_1s" 			: "如果你没有剩余的恐慌攻击，在战斗中每20秒会生成一个恐慌攻击。",
		"+_entropy_1" 			: "如果你剩余的恐慌攻击少于[VAL1]，在战斗中每20秒会生成一个恐慌攻击。",
		"+_entropy_2" 			: "这个效果在一场战斗内能够多次触发。",
		"+_panic_gain_s" 		: "每场战斗后获得1个恐慌攻击。",
		"+_panic_gain" 			: "每场战斗后获得[VAL1]个恐慌攻击。",
		"+_polyp_gain_s" 		: "每场战斗后获得1个|C3|恐慌之瘤。|C0|",
		"+_polyp_gain" 			: "每场战斗后获得[VAL1]个|C3|恐慌之瘤。|C0|",
		"=_auto_panic_1" 		: "在你受击时会自动使用恐慌攻击。",
		"=_auto_panic_2" 		: "在所有恐慌攻击用完之前，所有受击均会被阻挡。",
		
		"=_cant_panic_1" 		: "|C4|这个礼物生效时无法激活恐慌攻击。",
		"=_cant_panic_2" 		: "|C4|任何自动使用恐慌攻击的效果同样会失效。",
		"=_late_panic_1" 		: "|C4|在你受击一段时间后，自动使用恐慌攻击。",
		"=_late_panic_2" 		: "|C4|即使该受击被阻挡，这个效果也会触发。",
		"+_false_alarm_s" 		: "|C4|每场战斗中30秒后会自动使用一个恐慌攻击。",
		"+_false_alarm" 		: "|C4|每场战斗中每30秒会自动使用一个恐慌攻击，每场战斗最多[VAL1]个。",
		"+_panic_bleed" 		: "|C4|使用恐慌攻击会对你施加[VAL1]点|C3|流血生命。|C4|",
	},
	"charge_effects" : {
		"+_max_en" 				: "最大能量+[VAL1]",
		"+_en_rate" 			: "能量恢复加快[VAL1]%",
		"-_en_rate" 			: "|C4|能量恢复减慢[VAL1]%",
		"-%r_en_regen_time" 	: "收到这个礼物时，当前所需充满一单元能量的时间减少[VAL1]%。",
		"+_damage_scale" 		: "蓄力攻击造成[VAL1]%更多伤害",
		"-_damage_scale" 		: "|C4|蓄力攻击造成[VAL1]%更少伤害",
		"-%r_charge_time" 		: "收到这个礼物时，当前所需完整蓄力时间减少[VAL1]%。",
		"=_damage_type" 		: "蓄力射击伤害被转变为[ELEMENT[VAL1]]伤害",
		"+_part_en_rate" 		: "破坏部件能够恢复[VAL1]%更多能量",
		"-_part_en_rate" 		: "|C4|破坏部件能够恢复[VAL1]%更少能量",
		"+_love_signal_1" 		: "蓄力射击能够生成一个|C3|爱之信标，|C0|在18秒内吸引基础子弹与帮手子弹。",
		"+_love_signal_2" 		: "|C3|爱之信标|C0|在30像素半径范围内能够造成每秒12点[RADIANT]伤害。",
		"+_love_signal_3" 		: "被吸引的羽毛子弹有着额外射程。",
		"+_love_signal_4" 		: "按下蓄力射击键能够消除所有生效的|C3|爱之信标。|C0|",
		"+_leaky_charge" 		: "所有基础射击子弹在蓄力或维持蓄力时能够以50%射速继续发射。",
		"+_double_charge_1" 	: "使用两倍时间蓄力能够发射基于基础射击类型的|C3|暴击蓄力攻击|C0|并获得巨幅伤害加成！",
		"+_double_charge_2" 	: "使用能量发射的|C3|暴击蓄力攻击|C0|在命中时会生成大型|C3|暴击泡泡。|C0|",
		"+_double_charge_3" 	: "发射普通蓄力攻击会返还一半的能量。",
		"+_start_overflow" 		: "在每场战斗开始时，能量会完全恢复并溢出至[VAL1]单元。",
	
		"=_cant_charge" 		: "|C4|这个礼物生效时无法使用蓄力攻击。",
		"=_empty_battery" 		: "|C4|每场战斗开始时所有蓄力能量均会枯竭。溢出的能量会保留。",
	},
	"heart_effects" : {
		"=_active_1"			: "启用心型爱之子弹！",
		"=_active_2"			: "心心子弹有无尽的射程与平均的伤害。",
		"=_temp_active"			: "暂时启用心型爱之子弹！",
		"+_damage_raw" 			: "每个心心子弹伤害+[VAL1] ",
		"+_shot_rate" 			: "心心子弹射速+[VAL1]子弹每秒",
		"0_multi_rate_down_1" 	: "|C4|收到这个礼物时，你现有的心心射速减少[VAL1]%。",
		"0_multi_rate_down_2" 	: "|C4|当你已经有两倍子弹时这个效果减少到15%，有三倍或更多子弹时效果减少到10%。",
		"+_shot_speed" 			: "心心子弹速度+[VAL1]",
		"-_shot_speed" 			: "|C4|心心子弹速度-[VAL1]",
		"+_crit_rate" 			: "心心子弹变为|C3|暴击子弹|C0|的比率增加[VAL1]%",
		"+_crit_bonus" 			: "|C3|暴击心心子弹|C0|的额外伤害增加[VAL1]%",
		"+_split_burst_1s" 		: "在经过180像素后，心心子弹会分裂出1个额外的子弹。",
		"+_split_burst_1" 		: "在经过180像素后，心心子弹会分裂出[VAL1]个额外的子弹。",
		"+_split_burst_2" 		: "伤害会在全部分裂子弹间平均分配。",
		"+_focus_damage" 		: "专注模式下发射的心心子弹会造成[VAL1]%更多伤害。",
		"+_focus_size" 			: "专注模式下发射的心心子弹会变大[VAL1]%。",
		"+_focus_rate" 			: "保持专注时心心射速增加[VAL1]%。",
		"+_focus_split_s" 		: "保持专注时发射的心心子弹会会分裂出1个额外的子弹。",
		"+_focus_split" 		: "专注模式下发射的心心子弹会会分裂出[VAL1]个额外的子弹。",
		"+_focus_crit" 			: "保持专注时心心子弹变为|C3|暴击子弹|C0|的比率增加[VAL1]%",
		"+_shot_burst_1s" 		: "每次发射一个额外的心心",
		"+_shot_burst_1" 		: "每次发射[VAL1]个额外的心心",
		"+_shot_burst_2" 		: "心心子弹会在一定弧度内散射",
		"+_shot_spread" 		: "|C4|心心子弹的随机散射弧度增加[VAL1]度。",
		"=_damage_type" 		: "心心子弹伤害转变为[ELEMENT[VAL1]]伤害",
		"=_focus_type" 			: "专注模式下发射的心心子弹会造成[ELEMENT[VAL1]]伤害",
		"=_anchor" 				: "心心子弹的移动将锚定在你的位置。你移动时，子弹会随着你移动。",
		"=_sine_wave" 			: "心心子弹会波状移动。",
		"=_reflection_1" 		: "向你身后发射[VOID]心心子弹。",
		"=_reflection_2" 		: "后方射击有着80%的心心射速。",
		"=_reflection_3" 		: "如果主射击为[VOID]，后方射击将变为[RADIANT]",
		"=_cycle_element" 		: "每次发射的心心子弹会以下列顺序循环到另一元素：[RADIANT] → [VOID] → [BURN] → [ZAP] → [TOXIC]",
	},
	"feather_effects" : {
		"=_active_1"			: "启用短射程的羽毛子弹！",
		"=_active_2"			: "羽毛子弹在经过一段距离后会消失，但它们能够造成较高伤害。",
		"=_temp_active"			: "暂时启用短射程的羽毛子弹！",
		"+_damage_raw" 			: "每个羽毛子弹伤害+[VAL1] ",
		"+_shot_rate" 			: "羽毛子弹射速+[VAL1]爆发每秒",
		"-_shot_rate" 			: "|C4|羽毛子弹射速-[VAL1]爆发每秒",
		"-%_shot_rate" 			: "|C4|收到这个礼物时，你现有的羽毛射速减少[VAL1]%",
		"+_shot_range" 			: "羽毛射程+[VAL1]像素",
		"-%r_shot_range" 		: "|C4|收到这个礼物时，你现有的羽毛射程减少[VAL1]%",
		"+_shot_speed" 			: "羽毛子弹速度+[VAL1]",
		"-_shot_speed" 			: "|C4|羽毛子弹速度-[VAL1]",
		"+_shot_burst_s" 		: "每次爆发发射一根额外羽毛",
		"+_shot_burst" 			: "每次爆发发射[VAL1]根额外羽毛",
		"+_shot_spread" 		: "|C4|羽毛子弹的随机散射弧度增加[VAL1]度",
		"+_crit_rate" 			: "羽毛子弹变为|C3|暴击子弹|C0|的比率增加[VAL1]%",
		"+_crit_bonus" 			: "|C3|暴击羽毛子弹|C0|的额外伤害增加[VAL1]%",
		"+_focus_damage" 		: "专注模式下发射的羽毛子弹会造成[VAL1]%更多伤害。",
		"+_focus_size" 			: "专注模式下发射的羽毛子弹会变大[VAL1]%。",
		"+_focus_rate" 			: "保持专注时羽毛射速增加[VAL1]%。",
		"+_focus_range" 		: "保持专注时羽毛射程增加[VAL1]%。",
		"+_focus_crit" 			: "保持专注时羽毛子弹变为|C3|暴击子弹|C0|的比率增加[VAL1]%",
		"=_damage_type" 		: "羽毛子弹伤害转变为[ELEMENT[VAL1]]伤害。",
		"=_focus_type" 			: "专注模式下发射的羽毛子弹会造成[ELEMENT[VAL1]]伤害。",
		"=_cycle_element" 		: "每次爆发的羽毛子弹会以下列顺序循环到另一元素：[RADIANT] → [VOID] → [BURN] → [ZAP] → [TOXIC]",
		"=_endless_range_1" 	: "羽毛子弹现在有无尽的射程。",
		"=_endless_range_2" 	: "羽毛子弹在达到正常射程时会开始降低伤害。在达到两倍正常射程处伤害会降低至60%。",
		"=_endless_range_3" 	: "|C3|暴击羽毛子弹|C0|生成的|C3|暴击泡泡|C0|的伤害不会被该效果降低。",
		"=_crit_reach" 			: "所有|C3|暴击羽毛子弹|C0|有着三倍射程。",
	},
	"star_effects" : {
		"=_active_1"			: "启用星形爱之子弹！",
		"=_active_2"			: "只要你的心保持不动，星星子弹的射速就会不断增加。",
		"=_active_3"			: "移动将会快速降低积蓄的射速，在专注模式下移动时降低速度会更慢。",
		"=_temp_active"			: "暂时启用星型爱之子弹！",
		"+_damage_raw" 			: "每个星星子弹伤害+[VAL1] ",
		"+_min_rate" 			: "最小星星子弹射速+[VAL1]子弹每秒",
		"-_min_rate" 			: "|C4|最小星星子弹射速-[VAL1]子弹每秒",
		"+_max_rate" 			: "最大星星子弹射速+[VAL1]子弹每秒",
		"-_max_rate" 			: "|C4|最大星星子弹射速-[VAL1]子弹每秒",
		"-%r_rate_time" 		: "收到这个礼物时，你现有需要达到最大射速的时间减少[VAL1]%。",
		"+_shot_speed" 			: "星星子弹速度+[VAL1]",
		"-_shot_speed" 			: "|C4|星星子弹速度-[VAL1]",
		"+_shot_size" 			: "星星子弹变大[VAL1]%。",
		"+_shot_spread" 		: "|C4|星星子弹的随机散射弧度增加[VAL1]度。",
		"-%_shot_spread" 		: "收到这个礼物时，现有星星子弹的随机散射弧度减少[VAL1]%。",
		"+%_shot_spread" 		: "|C4|收到这个礼物时，现有星星子弹的随机散射弧度增加[VAL1]%。",
		"+_crit_rate" 			: "星星子弹变为|C3|暴击子弹|C0|的比率增加[VAL1]%",
		"+_crit_bonus" 			: "|C3|暴击星星子弹|C0|的额外伤害增加[VAL1]%",
		"+_focus_damage" 		: "专注模式下发射的星星子弹会造成[VAL1]%更多伤害。",
		"+_focus_size" 			: "专注模式下发射的星星子弹会变大[VAL1]%。",
		"+_focus_rate" 			: "保持专注时星星射速增加[VAL1]%。",
		"+_focus_fill" 			: "保持专注时星星射速条增长速度[VAL1]%。",
		"+_focus_crit" 			: "保持专注时星星子弹变为|C3|暴击子弹|C0|的比率增加[VAL1]%",
		"=_damage_type" 		: "星星子弹伤害转变为[ELEMENT[VAL1]]伤害",
		"=_focus_type" 			: "专注模式下发射的星星子弹会造成[ELEMENT[VAL1]]伤害",
		"=_star_glyph" 			: "向你身后以80%的现有星星射速发射星星子弹",
		"=_photon_wave" 		: "星星子弹会波状移动。",
		"=_cycle_element" 		: "每次发射的星星子弹会以下列顺序循环到另一元素：[RADIANT] → [VOID] → [BURN] → [ZAP] → [TOXIC]",
		"+_rock_star_1" 		: "移动时星星射速条降低速度变为原本的50%。",
		"+_rock_star_2" 		: "专注移动时星星射速条降低速度从原本的50%变为33.3%。",
	},
	"helper_effects" : {
		"+_damage_scale" 		: "所有帮手攻击造成[VAL1]%更多伤害。",
		"-_damage_scale" 		: "|C4|所有帮手攻击造成[VAL1]%更少伤害。",
		"+_rate_scale" 			: "所有帮手的射速及最大射速增加[VAL1]%。",
		"-_rate_scale" 			: "|C4|所有帮手的射速及最大射速减少[VAL1]%。",
		"+_shot_size"			: "所有帮手子弹变大[VAL1]%。",
		"+_focus_damage" 		: "专注模式下所有帮手攻击造成[VAL1]%更多伤害。",
		"+_focus_rate" 			: "专注模式下所有帮手的射速及最大射速增加[VAL1]%。",
		"+_focus_size" 			: "专注模式下所有帮手子弹变大[VAL1]%。",
		"+_separation" 			: "帮手间的距离增加[VAL1]像素。",
		"-%_separation" 		: "帮手间的距离减少[VAL1]%。",
		"+_chain_multi_1s" 		: "每场战斗开始时生成你|C3|帮手链|C0|中前[VAL_CAP1]个帮手的额外复制。",
		"+_chain_multi_1" 		: "每场战斗开始时生成你|C3|帮手链|C0|中前[VAL_CAP1]个帮手的[VAL1]个额外复制。",
		"+_chain_multi_2" 		: "对于在战斗中生成帮手的效果，其上限会增加[VAL_CAP2]%",
		"+_chain_multi_3" 		: "每种特别|C3|围绕型帮手|C0|同样能将上限增加[VAL_CAP3]。",
		"+_chain_multi_4" 		: "其他特别帮手可能会以其他方式被增加。",
		"H_radiant_stone_s" 	: "生成一个心型石帮手！",
		"H_radiant_stone" 		: "生成[VAL1]个心型石帮手！",
		"H_void_stone_s" 		: "生成一个空无石帮手！",
		"H_void_stone" 			: "生成[VAL1]个空无石帮手！",
		"H_burn_stone_s" 		: "生成一个热量石帮手！",
		"H_burn_stone" 			: "生成[VAL1]个热量石帮手！",
		"H_zap_stone_s" 		: "生成一个电弧石帮手！",
		"H_zap_stone" 			: "生成[VAL1]个电弧石帮手！",
		"H_toxic_stone_s" 		: "生成一个灾厄石帮手！",
		"H_toxic_stone" 		: "生成[VAL1]个灾厄石帮手！",
		"0_normal_stone" 		: "它会每秒发射[VAL_RATE]子弹，每个子弹造成[VAL_DMG][ELEMENT[VAL1]]伤害。",
		"0_multi_stones" 		: "它们会每秒发射[VAL_RATE]子弹，每个子弹造成[VAL_DMG][ELEMENT[VAL1]]伤害。",
		"0_common_stones" 		: "普通石头帮手会每秒发射[VAL_RATE]子弹，每个子弹造成[VAL_DMG]相应元素伤害。",
		"H_all_stone_s" 		: "生成一个全能石帮手！",
		"H_all_stone" 			: "生成[VAL1]个全能石帮手！",
		"0_all_stone_1" 		: "全能石帮手的子弹造成[VAL_DMG]伤害且会在所有元素类型间循环。",
		"0_all_stone_2" 		: "它们的射速一开始为[VAL_MIN]，且随着现有连击而增加，最大达到[VAL_MAX]子弹每秒。|L|（在75%连击达到上限）",
		"H_random_stone_1s" 	: "生成[VAL1]个随机石头帮手，每场战斗开始时都会随机。",
		"H_random_stone_1" 		: "生成[VAL1]个随机石头帮手，每场战斗开始时都会随机。",
		"H_random_stone_2" 		: "随机石头帮手会是以下的其中一个：|L||I11||C11|心型石|C0| - 19%|L||I12||C12|空无石|C0| - 19%|L||I13||C13|热量石|C0| - 19%|L||I14||C14|电弧石|C0| - 19%|L||I15||C15|灾厄石|C0| - 19%|L||C3|全能石|C0| - 5%",
		"H_broken_heart_1" 		: "生成一个破碎之心帮手",
		"H_broken_heart_2" 		: "她会发射[VAL_BURST]子弹，每个在[VAL_DMG][RADIANT]伤害与[VAL_DMG][VOID]伤害之间循环",
		"H_broken_heart_3" 		: "它们的射速一开始为[VAL_MIN]，且随着怪物恐惧降低而增加，最大达到[VAL_MAX]子弹每秒。|L|（在20%恐惧达到上限）",
		"H_cross_twin_1s" 		: "生成一个交叉双子帮手！",
		"H_cross_twin_1" 		: "生成[VAL1]个交叉双子帮手！",
		"H_cross_twin_2" 		: "在你受击（即使被阻挡）或使用恐慌攻击后，交叉双子会激活。",
		"H_cross_twin_3" 		: "交叉双子每秒发射[VAL_RATE]子弹，每个子弹造成[VAL_DMG][TOXIC]伤害。",
		"H_split_unit_s" 		: "生成一个分裂单元帮手！",
		"H_split_unit" 			: "生成[VAL1]个分裂单元帮手！",
		"0_split_unit" 			: "分裂单元每次爆裂发射[VAL_BURST]子弹，每个子弹造成[VAL_DMG][ZAP]伤害，射速为每秒[VAL_RATE]次爆裂。",
		"H_inverted_unit_s" 	: "生成一个反转单元帮手！",
		"H_inverted_unit" 		: "生成[VAL1]个反转单元帮手！",
		"0_inverted_unit" 		: "反转单元每秒向后发射[VAL_RATE]子弹，每个子弹造成[VAL_DMG][ZAP]伤害。.",
		"H_scrambla_helper_s" 	: "生成一个蛋花帮手！",
		"H_scrambla_helper" 	: "生成[VAL1]个蛋花帮手！",
		"0_scrambla_helper_1" 	: "蛋花每秒发射[VAL_MIN]子弹，每个子弹造成[VAL_DMG][TOXIC]伤害。",
		"0_scrambla_helper_2" 	: "战斗中每破坏一个怪物部件，她们的射速会上升0.5。|L|（最大达到每秒[VAL_MAX]子弹）",
		"H_boiler_helper_s" 	: "生成一个锅炉帮手！",
		"H_boiler_helper" 		: "生成[VAL1]个锅炉帮手！",
		"0_boiler_helper_1" 	: "锅炉每秒发射[VAL_MIN]子弹，每个子弹造成[VAL_DMG][BURN]伤害。",
		"0_boiler_helper_2" 	: "你每次在战斗中受击，她们的射速会上升2。|L|（最大达到每秒[VAL_MAX]子弹）",
		"H_burdened_helper_s" 	: "生成一个负担帮手",
		"H_burdened_helper" 	: "生成[VAL1]个负担帮手",
		"0_burdened_helper_1" 	: "负担帮手每秒发射[VAL_MIN]子弹，每个子弹造成[VAL_DMG][VOID]伤害。",
		"0_burdened_helper_2" 	: "|C4|触碰它们会对你施加2点[VOID]伤害，|C0|但也会将其射速提升至每秒[VAL_MAX]子弹。",
		"H_filler_helper_s" 	: "生成一个填充帮手",
		"H_filler_helper" 		: "|C4|生成[VAL1]个填充帮手",
		"0_filler_helper" 		: "|C4|填充帮手会被添加至|C3|帮手链|C4|的前端且不会发射任何子弹。",
		"H_stymie_helper_s" 	: "创造一个阻碍帮手",
		"H_stymie_helper" 		: "创造[VAL1]个阻碍帮手",
		"0_stymie_helper_1" 	: "阻碍帮手每秒发射[VAL_MAX]子弹，每个子弹造成[VAL_DMG][BURN]伤害，但仅当她们在你的心前面时才会发射。",
		"0_stymie_helper_2" 	: "|C4|阻碍帮手会被添加至|C3|帮手链|C4|的前端且能够阻挡你的子弹。",
		"+_photo_stones_s" 		: "你在战斗中的首个蓄力攻击能够生成1个相片石。",
		"+_photo_stones" 		: "你在战斗中的前[VAL1]个蓄力攻击能够生成最多[VAL1]个相片石。",
		"0_photo_stones_1" 		: "相片石在正常战斗中都会停留在原位。",
		"0_photo_stones_2" 		: "相片石每秒发射[VAL_RATE]子弹，每个子弹造成[VAL_DMG]伤害，元素类型与你的蓄力攻击相同。",
		"+_negatives_s" 		: "每场战斗会生成一个负片石。",
		"+_negatives" 			: "每场战斗会生成[VAL1]个负片石。",
		"0_negatives_1" 		: "每当怪物的恐惧下降10%时会生成一个负片石。",
		"0_negatives_2" 		: "负片石每秒发射[VAL_RATE]子弹，每个子弹造成[VAL_DMG][VOID]伤害。",
		"0_negatives_3" 		: "|C4|负片石会停留在原地且能够阻挡你的子弹。",
		"+_blue_helpers_1" 		: "她们每个都能每秒发射[VAL_RATE]子弹，每个子弹造成[VAL_DMG][RADIANT]或[VOID]伤害。",
		"+_blue_helpers_2" 		: "达成50%连击时获得1个蓝色维目尔帮手，但仅当全连击结束战斗时她才会留下！|L|（最大8个）",
		"+_misfits_1" 			: "她们每个都能每秒发射[VAL_RATE]子弹，每个子弹造成[VAL_DMG][VOID]或[ZAP]伤害。",
		"+_misfits_2" 			: "当你恐慌攻击时获得1个不具之心|L|当你受到伤害时获得2个不具之心|L|（最大12个）",
		"+_misfits_3" 			: "|C4|若数量大于2，在战斗结束时会失去一个不具之心|L|大于8时会再失去一个",
		"+_mite_helpers" 		: "在战斗中吸引最多[VAL1]个跳虫帮手。",
		"0_mite_helpers_1" 		: "每次你的连击增加10%时，1个跳虫帮手就会出现。",
		"0_mite_helpers_2" 		: "每个跳虫帮手有着随机的元素，能够每秒发射[VAL_RATE]子弹，每个子弹造成[VAL_DMG]的对应元素伤害。",
		"0_mite_helpers_3" 		: "|C4|当大于10%的连击结束时失去3个跳虫帮手，包括战斗结束。",
		"+_stone_magnet" 		: "在战斗中吸引最多[VAL1]个磁力石。",
		"0_stone_magnet_1" 		: "磁力石每秒发射[VAL_RATE]子弹，每个子弹造成[VAL_DMG][RADIANT]或[VOID]伤害。",
		"0_stone_magnet_2" 		: "能够生成磁力石的行为：|L|消除怪物1%的恐惧时生成1个|L|每额外25%恐惧值生成一个|L|每个被破坏的部件生成1个",
		"0_stone_magnet_3" 		: "|C4|战斗结束时所有磁力石均被重置。",
		"+_umbrella" 			: "在场地的左上角生成一个临时的安全泡泡。",
		"+_fallen_angel" 		: "在场地的左下角生成一个临时的安全泡泡。",
		"0_safety_bubble_1" 	: "安全泡泡能够持续[BUBBLE_DURATION]秒。",
		"0_safety_bubble_2" 	: "泡泡可以伤害触碰它的怪物，每秒[BUBBLE_DAMAGE][VOID]伤害。",
		"0_safety_bubble_3" 	: "|C4|当你在其中躲藏时，或伤害怪物时，它消失的速度会变为4倍。",
		"0_safety_bubble_4" 	: "|C4|怪物的恐惧降至15%时，它会立刻消失。",
		"=_ring_form" 			: "你的|C3|帮手链|C0|会环绕着你。",
		"=_sine_wave" 			: "所有帮手的子弹会波状移动。",
		"+_bullet_warp_1" 		: "当帮手的子弹离开屏幕时，它们会被传送到另一边。",
		"+_bullet_warp_2s" 		: "每个子弹仅能水平传送1次，但垂直传送没有次数限制。",
		"+_bullet_warp_2" 		: "每个子弹仅能水平传送[VAL1]次，但垂直传送没有次数限制。",
	},
	"tetrid_effects" : {
		"tet_green" 			: "获得[VAL1]个[TET_COLOR0]魔尘",
		"tet_red" 				: "获得[VAL1]个[TET_COLOR1]魔尘",
		"tet_yellow" 			: "获得[VAL1]个[TET_COLOR2]魔尘",
		"tet_blue" 				: "获得[VAL1]个[TET_COLOR3]魔尘",
		"tet_orange" 			: "获得[VAL1]个[TET_COLOR4]魔尘",
		"tet_purple" 			: "获得[VAL1]个[TET_COLOR5]魔尘",
		"tet_radiant" 			: "获得[VAL1]个[TET_COLOR6]魔尘",
		"tet_tetrid_s" 			: "这些魔尘能够正好组成1个棱晶",
		"tet_tetrid" 			: "这些魔尘能够正好组成[VAL1]个棱晶",
		"tet_multi" 			: "这些魔尘能够正好组成每种颜色的1个棱晶",
	},
	"reroll_effects" : {
		"R_lv_down" 			: "基础怪物等级降低[VAL1]",
		"R_lv_up" 				: "基础怪物等级增加[VAL1]",
		"R_monsters" 			: "所有怪物卡被随机重掷为不同的怪物，重掷后的怪物不会包含当前任何怪物。",
		"0_monsters" 			: "如果可用怪物池不足，那它将在重掷前刷新。",
		"R_gifts" 				: "所有怪物提供的礼物被重掷。重掷后的|C3|力量礼物|C0|不会包含当前任何力量礼物。",
		"R_xatk_down" 			: "这个礼物生效时，所有怪物的|C3|攻击速度力量|C0|减少[VAL1]。",
		"0_xatk_down" 			: "每级会使所有怪物的子弹移动速度降低10%|L|（最大-50%）",
		"R_xdmg_down" 			: "这个礼物生效时，所有怪物的|C3|攻击伤害力量|C0|减少[VAL1]。",
		"0_xdmg_down" 			: "每级会使从任何攻击处受到的伤害降低20%|L|（最大-50%）",
		"R_xdef_down" 			: "这个礼物生效时，所有怪物的|C3|恐惧力量|C0|减少[VAL1]。",
		"0_xdef_down" 			: "每级会使怪物的总恐惧值降低20%|L|（最大-50%）",
		"0_xlv_down" 			: "这个效果可能导致怪物的等级降低。",
		"R_xatk_up" 			: "|C4|这个礼物生效时，所有怪物的|C3|攻击速度力量|C4|增加[VAL1]。",
		"0_xatk_up" 			: "|C4|每级会使所有怪物的子弹移动速度增加10%",
		"R_xdmg_up" 			: "|C4|这个礼物生效时，所有怪物的|C3|攻击伤害力量|C4|增加[VAL1]。",
		"0_xdmg_up" 			: "|C4|每级会使从任何攻击处受到的伤害增加20%",
		"R_xdef_up" 			: "|C4|这个礼物生效时，所有怪物的|C3|恐惧力量|C4|增加[VAL1]。",
		"0_xdef_up" 			: "|C4|每级会使怪物的总恐惧值增加20%",
		"0_xlv_up" 				: "|C4|这个效果可能导致怪物的等级升高。",
	},
	"bounty_effects" : {
		"+_extra_motes" 		: "这个效果生效时，所有提取手段获得的魔尘增加[VAL1]%。",
		"=_extra_type" 			: "这个效果让你获得的额外魔尘会是[TET_COLOR[VAL1]]魔尘.",
		"+_combo_extra" 		: "这个效果生效时，从任何爱之连击提取的魔尘增加[VAL1]%。",
		"=_combo_type" 			: "所有从爱之连击获得的魔尘都会是[TET_COLOR[VAL1]]魔尘.",
		"+_radiant_ratio" 		: "[VAL1]%提取的魔尘会被转变为光耀魔尘。",
		"0_radiant_ratio" 		: "对于能够给出光耀魔尘的怪物，该比率仍会适用于其剩余魔尘。",
	},
	
}