{
	"script" : [
		{
			"use_textbox"	: 1,
			"play_music"	: "tutorbot_scene_music",
			"bg_image"		: "spr_tutorial_common",
			"character"		: ["VOICE_bot", "CHAR_tutor_right", "MOOD_normal"],
			"dialog"		: "年幼的扎拉登，     看起来有些怪物们为你准备了一场游戏。",
		},
		{
			"character"		: ["VOICE_blank", "CHAR_blank_left", "MOOD_surprised"],
			"dialog"		: "游戏？    是什么样的游戏？",
		},
		{
			"character"		: ["VOICE_bot", "CHAR_tutor_right", "MOOD_normal"],
			"dialog"		: "它叫做|C3|快速挑战。",
		},
		{
			"character"		: ["VOICE_blank", "CHAR_blank_left", "MOOD_very_happy"],
			"dialog"		: "|wave|那听起来很有趣！|norm|我要怎么玩呢？",
		},
		{
			"character"		: ["VOICE_bot", "CHAR_tutor_right", "MOOD_normal"],
			"dialog"		: "本单元现在将解释|C3|快速挑战。",
		},
		{
			"character"		: ["VOICE_bot", "CHAR_tutor_right", "MOOD_normal"],
			"dialog"		: "在|C3|快速挑战|C0|中，你可以随时爱任何怪物。|!| 前提是你已经|C3|点亮|C0|了她们的卡片。",
		},
		{
			"character"		: ["VOICE_bot", "CHAR_tutor_right", "MOOD_normal"],
			"dialog"		: "你同样也可以使用任何|C3|点亮的力量礼物|C0|来帮助你去爱它们。",
		},
		{
			"character"		: ["VOICE_bot", "CHAR_tutor_right", "MOOD_normal"],
			"dialog"		: "从怪物处获得高分能够让你获得|C3|徽章|C0|并且|C3|升级。",
		},
		{
			"character"		: ["VOICE_bot", "CHAR_tutor_right", "MOOD_normal"],
			"dialog"		: "当你|C3|升级|C0|时，你每场战斗能够|C3|装备更多力量礼物。|C0|",
		},
		{
			"play_music"	: "silence",
			"character"		: ["VOICE_blank", "CHAR_blank_left", "MOOD_happy_cry1"],
			"dialog"		: ".  .  .",
		},
		{
			"character"		: ["VOICE_bot", "CHAR_tutor_right", "MOOD_normal"],
			"dialog"		: "本单元从你的表情中检测到错误。",
		},
		{
			"play_music"	: "scene_music_b",
			"character"		: ["VOICE_blank", "CHAR_blank_left", "MOOD_happy_cry1"],
			"dialog"		: "她们想让我再爱她们一遍？",
		},
		{
			"character"		: ["VOICE_bot", "CHAR_tutor_right", "MOOD_normal"],
			"dialog"		: "错误解除。    |L|检测到高兴的泪水。",
		},
		{
			"character"		: ["VOICE_blank", "CHAR_blank_left", "MOOD_happy_cry2"],
			"dialog"		: "嘿，小机器人——",
		},
		{
			"character"		: ["VOICE_blank", "CHAR_blank_left", "MOOD_happy_cry3"],
			"dialog"		: "|wave|我爱你。",
		},
		{
			"character"		: ["VOICE_bot", "CHAR_tutor_right", "MOOD_normal"],
			"dialog"		: "|C3|建议:|C0|给这个单元一个拥抱。",
		},
		{
			"character"		: ["VOICE_blank", "CHAR_blank_left", "MOOD_happy_cry3"],
			"dialog"		: "当然了。",
		},
		{
			"love_hearts"	: 1,
			"character"		: ["VOICE_bot", "CHAR_tutor_right", "MOOD_blush"],
			"dialog"		: "拥抱完成。",
		},
	]
}